cambridge_mask_stats/__init__.py
cambridge_mask_stats/main.py
cambridge_mask_stats/program.py
cambridge_mask_stats-0.10.2.dist-info/LICENSE
cambridge_mask_stats-0.10.2.dist-info/METADATA
cambridge_mask_stats-0.10.2.dist-info/WHEEL
cambridge_mask_stats-0.10.2.dist-info/entry_points.txt
cambridge_mask_stats-0.10.2.dist-info/top_level.txt
cambridge_mask_stats-0.10.2.dist-info/RECORD
