Metadata-Version: 2.1
Name: cambridge-mask-stats
Version: 0.10.2
Summary: Program to output the wearing time and other statistics of a Cambridge N99 | FFP2 mask.
Home-page: https://github.com/w01fdev/cambridge-mask-stats
Author: w01f
Author-email: w01f@w01f.dev
License: GPL-3.0
Platform: UNKNOWN
Classifier: Development Status :: 3 - Alpha
Classifier: Programming Language :: Python :: 3.6
Classifier: Programming Language :: Python :: 3.7
Classifier: Programming Language :: Python :: 3.8
Classifier: Programming Language :: Python :: 3.9
Requires-Python: >=3.6
License-File: LICENSE
Requires-Dist: numpy
Requires-Dist: pandas
Requires-Dist: python-dateutil
Requires-Dist: pytz
Requires-Dist: six
